[
  {
    "img": "https://cdn.assunnahfoundation.org/gallery/iftar_gallery_1.jpg",
    "type": "iftar"
  },
  {
    "img": "https://cdn.assunnahfoundation.org/gallery/iftar_gallery_2.jpg",
    "type": "iftar"
  },
  {
    "img": "https://cdn.assunnahfoundation.org/gallery/iftar_gallery_3.jpg",
    "type": "iftar"
  },
  {
    "img": "https://cdn.assunnahfoundation.org/gallery/iftar_gallery_4.jpg",
    "type": "iftar"
  },
  {
    "img": "https://cdn.assunnahfoundation.org/gallery/iftar_gallery_5.jpg",
    "type": "iftar"
  },
  {
    "img": "https://cdn.assunnahfoundation.org/gallery/iftar_gallery_6.jpg",
    "type": "iftar"
  },
  {
    "img": "https://cdn.assunnahfoundation.org/gallery/iftar_gallery_6.jpg",
    "type": "iftar"
  },
  {
    "img": "https://cdn.assunnahfoundation.org/gallery/iftar_gallery_7.jpg",
    "type": "iftar"
  },
  {
    "img": "https://cdn.assunnahfoundation.org/gallery/orphan_gallery_1.jpg",
    "type": "orphans"
  },
  {
    "img": "https://cdn.assunnahfoundation.org/gallery/orphan_gallery_1.jpg",
    "type": "orphans"
  },
  {
    "img": "https://cdn.assunnahfoundation.org/gallery/qurbani_gallery_1.jpg",
    "type": "qurbani"
  },
  {
    "img": "https://cdn.assunnahfoundation.org/gallery/qurbani_gallery_2.jpg",
    "type": "qurbani"
  },
  {
    "img": "https://cdn.assunnahfoundation.org/gallery/qurbani_gallery_3.jpg",
    "type": "qurbani"
  },
  {
    "img": "https://cdn.assunnahfoundation.org/gallery/qurbani_gallery_4.jpg",
    "type": "qurbani"
  },
  {
    "img": "https://cdn.assunnahfoundation.org/gallery/qurbani_gallery_5.jpg",
    "type": "qurbani"
  },
  {
    "img": "https://cdn.assunnahfoundation.org/gallery/qurbani_gallery_5.jpg",
    "type": "food"
  },
  {
    "img": "https://cdn.assunnahfoundation.org/gallery/food_distribution_gallery_2.jpg",
    "type": "food"
  },
  {
    "img": "https://cdn.assunnahfoundation.org/gallery/food_distribution_gallery_3.jpg",
    "type": "food"
  },
  {
    "img": "https://cdn.assunnahfoundation.org/gallery/food_distribution_gallery_4.jpg",
    "type": "food"
  },
  {
    "img": "https://cdn.assunnahfoundation.org/gallery/food_distribution_gallery_5.jpg",
    "type": "food"
  },
  {
    "img": "https://cdn.assunnahfoundation.org/gallery/tube_well_distribution_gallery_1.jpg",
    "type": "tubeWell"
  },
  {
    "img": "https://cdn.assunnahfoundation.org/gallery/tube_well_distribution_gallery_2.jpg",
    "type": "tubeWell"
  },
  {
    "img": "https://cdn.assunnahfoundation.org/gallery/tube_well_distribution_gallery_3.jpg",
    "type": "tubeWell"
  },
  {
    "img": "https://cdn.assunnahfoundation.org/gallery/tube_well_distribution_gallery_4.jpg",
    "type": "tubeWell"
  },
  {
    "img": "https://cdn.assunnahfoundation.org/gallery/tube_well_distribution_gallery_5.jpg",
    "type": "tubeWell"
  },
  {
    "img": "https://cdn.assunnahfoundation.org/gallery/tube_well_distribution_gallery_6.jpg",
    "type": "tubeWell"
  },
  {
    "img": "https://cdn.assunnahfoundation.org/gallery/relief_distribution_gallery_1.jpg",
    "type": "relif"
  },
  {
    "img": "https://cdn.assunnahfoundation.org/gallery/relief_distribution_gallery_2.jpg",
    "type": "relif"
  },
  {
    "img": "https://cdn.assunnahfoundation.org/gallery/relief_distribution_gallery_3.jpg",
    "type": "relif"
  },
  {
    "img": "https://cdn.assunnahfoundation.org/gallery/relief_distribution_gallery_4.jpg",
    "type": "relif"
  },
  {
    "img": "https://cdn.assunnahfoundation.org/gallery/relief_distribution_gallery_5.jpg",
    "type": "relif"
  },
  {
    "img": "https://cdn.assunnahfoundation.org/gallery/relief_distribution_gallery_6.jpg",
    "type": "relif"
  },
  {
    "img": "https://cdn.assunnahfoundation.org/gallery/relief_distribution_gallery_7.jpg",
    "type": "relif"
  },
  {
    "img": "https://cdn.assunnahfoundation.org/gallery/relief_distribution_gallery_8.jpg",
    "type": "relif"
  },
  {
    "img": "https://cdn.assunnahfoundation.org/gallery/van_distribution_gallery_1.jpg",
    "type": "van"
  },
  {
    "img": "https://cdn.assunnahfoundation.org/gallery/van_distribution_gallery_2.jpg",
    "type": "van"
  },
  {
    "img": "https://cdn.assunnahfoundation.org/gallery/van_distribution_gallery_3.jpg",
    "type": "van"
  },
  {
    "img": "https://cdn.assunnahfoundation.org/gallery/van_distribution_gallery_4.jpg",
    "type": "van"
  },
  {
    "img": "https://cdn.assunnahfoundation.org/gallery/winter_clothing_gallery_1.jpg",
    "type": "winter"
  },
  {
    "img": "https://cdn.assunnahfoundation.org/gallery/winter_clothing_gallery_2.jpg",
    "type": "winter"
  },
  {
    "img": "https://cdn.assunnahfoundation.org/gallery/winter_clothing_gallery_2.jpg",
    "type": "winter"
  },
  {
    "img": "https://cdn.assunnahfoundation.org/gallery/winter_clothing_gallery_4.jpg",
    "type": "winter"
  },
  {
    "img": "https://cdn.assunnahfoundation.org/gallery/winter_clothing_gallery_5.jpg",
    "type": "winter"
  },
  {
    "img": "https://cdn.assunnahfoundation.org/gallery/winter_clothing_gallery_6.jpg",
    "type": "winter"
  },
  {
    "img": "https://cdn.assunnahfoundation.org/gallery/winter_clothing_gallery_7.jpg",
    "type": "winter"
  },
  {
    "img": "https://cdn.assunnahfoundation.org/gallery/winter_clothing_gallery_8.jpg",
    "type": "winter"
  },
  {
    "img": "https://cdn.assunnahfoundation.org/gallery/winter_clothing_gallery_9.jpg",
    "type": "winter"
  },
  {
    "img": "https://cdn.assunnahfoundation.org/gallery/winter_clothing_gallery_10.jpg",
    "type": "winter"
  },
  {
    "img": "https://cdn.assunnahfoundation.org/gallery/winter_clothing_gallery_11.jpg",
    "type": "winter"
  }
]
